{
"meta":{"test_sets":[],"test_metrics":[],"learn_metrics":[{"best_value":"Min","name":"MultiClass"}],"launch_mode":"Train","parameters":"","iteration_count":100,"learn_sets":["learn"],"name":"experiment"},
"iterations":[
{"learn":[0.6939646104],"iteration":0,"passed_time":0.00841258601,"remaining_time":0.832846015},
{"learn":[0.477493347],"iteration":1,"passed_time":0.01396917223,"remaining_time":0.6844894394},
{"learn":[0.3946588011],"iteration":2,"passed_time":0.02180952866,"remaining_time":0.70517476},
{"learn":[0.3319374047],"iteration":3,"passed_time":0.02674106477,"remaining_time":0.6417855546},
{"learn":[0.2745759526],"iteration":4,"passed_time":0.03227507638,"remaining_time":0.6132264513},
{"learn":[0.2434827236],"iteration":5,"passed_time":0.04127424353,"remaining_time":0.6466298153},
{"learn":[0.2182787112],"iteration":6,"passed_time":0.04741130009,"remaining_time":0.6298929869},
{"learn":[0.1998170443],"iteration":7,"passed_time":0.05623873461,"remaining_time":0.646745448},
{"learn":[0.1830053528],"iteration":8,"passed_time":0.06197344932,"remaining_time":0.626620432},
{"learn":[0.1644992252],"iteration":9,"passed_time":0.07044055221,"remaining_time":0.6339649699},
{"learn":[0.1580068745],"iteration":10,"passed_time":0.07612108017,"remaining_time":0.6158887396},
{"learn":[0.1482157623],"iteration":11,"passed_time":0.08801255175,"remaining_time":0.6454253795},
{"learn":[0.139096602],"iteration":12,"passed_time":0.09573567873,"remaining_time":0.6406926192},
{"learn":[0.1328038595],"iteration":13,"passed_time":0.1046147601,"remaining_time":0.6426335266},
{"learn":[0.1252399012],"iteration":14,"passed_time":0.1105229609,"remaining_time":0.6262967786},
{"learn":[0.1155077918],"iteration":15,"passed_time":0.1188431239,"remaining_time":0.6239264003},
{"learn":[0.1132030288],"iteration":16,"passed_time":0.1244145673,"remaining_time":0.6074358288},
{"learn":[0.1046241572],"iteration":17,"passed_time":0.1339631451,"remaining_time":0.61027655},
{"learn":[0.09459579865],"iteration":18,"passed_time":0.140125477,"remaining_time":0.5973770337},
{"learn":[0.08986359631],"iteration":19,"passed_time":0.1460190409,"remaining_time":0.5840761635},
{"learn":[0.08285663841],"iteration":20,"passed_time":0.1572775951,"remaining_time":0.5916633339},
{"learn":[0.0779517511],"iteration":21,"passed_time":0.1669547898,"remaining_time":0.5919306182},
{"learn":[0.0758477804],"iteration":22,"passed_time":0.1754194049,"remaining_time":0.5872736598},
{"learn":[0.07268046094],"iteration":23,"passed_time":0.1851916813,"remaining_time":0.5864403241},
{"learn":[0.06786223912],"iteration":24,"passed_time":0.1901604099,"remaining_time":0.5704812298},
{"learn":[0.06528406465],"iteration":25,"passed_time":0.1992448332,"remaining_time":0.5670814484},
{"learn":[0.06170899691],"iteration":26,"passed_time":0.2025450342,"remaining_time":0.5476217591},
{"learn":[0.05731218563],"iteration":27,"passed_time":0.2073389172,"remaining_time":0.5331572157},
{"learn":[0.05621870474],"iteration":28,"passed_time":0.2142341407,"remaining_time":0.5245042755},
{"learn":[0.05541909924],"iteration":29,"passed_time":0.2205766693,"remaining_time":0.514678895},
{"learn":[0.05255560024],"iteration":30,"passed_time":0.224778507,"remaining_time":0.500313451},
{"learn":[0.05061179263],"iteration":31,"passed_time":0.2342489371,"remaining_time":0.4977789914},
{"learn":[0.04829757457],"iteration":32,"passed_time":0.2398205285,"remaining_time":0.4869083457},
{"learn":[0.04468208168],"iteration":33,"passed_time":0.2478263508,"remaining_time":0.481074681},
{"learn":[0.04295721001],"iteration":34,"passed_time":0.2528384019,"remaining_time":0.469557032},
{"learn":[0.04125693031],"iteration":35,"passed_time":0.2647554666,"remaining_time":0.470676385},
{"learn":[0.04023086297],"iteration":36,"passed_time":0.2736621646,"remaining_time":0.4659653072},
{"learn":[0.03840555495],"iteration":37,"passed_time":0.2820113955,"remaining_time":0.4601238557},
{"learn":[0.03664037775],"iteration":38,"passed_time":0.2886269945,"remaining_time":0.4514422221},
{"learn":[0.03582233828],"iteration":39,"passed_time":0.2979408517,"remaining_time":0.4469112775},
{"learn":[0.0346319205],"iteration":40,"passed_time":0.3036910855,"remaining_time":0.4370188792},
{"learn":[0.03355629767],"iteration":41,"passed_time":0.3110871053,"remaining_time":0.4295964787},
{"learn":[0.03188360364],"iteration":42,"passed_time":0.3144891774,"remaining_time":0.4168810026},
{"learn":[0.03096323051],"iteration":43,"passed_time":0.3176801497,"remaining_time":0.4043201905},
{"learn":[0.02916297001],"iteration":44,"passed_time":0.3210834442,"remaining_time":0.3924353206},
{"learn":[0.02847958622],"iteration":45,"passed_time":0.3275881014,"remaining_time":0.3845599451},
{"learn":[0.02761872965],"iteration":46,"passed_time":0.3309460895,"remaining_time":0.3731945264},
{"learn":[0.02742028213],"iteration":47,"passed_time":0.3341505594,"remaining_time":0.3619964394},
{"learn":[0.02668577333],"iteration":48,"passed_time":0.3376533511,"remaining_time":0.3514351206},
{"learn":[0.02550348845],"iteration":49,"passed_time":0.3430783136,"remaining_time":0.3430783136},
{"learn":[0.02504482241],"iteration":50,"passed_time":0.3465532093,"remaining_time":0.3329628874},
{"learn":[0.02437661788],"iteration":51,"passed_time":0.3498643548,"remaining_time":0.3229517121},
{"learn":[0.02398405245],"iteration":52,"passed_time":0.3531686401,"remaining_time":0.3131872846},
{"learn":[0.02355332603],"iteration":53,"passed_time":0.3594433023,"remaining_time":0.3061924427},
{"learn":[0.02296619637],"iteration":54,"passed_time":0.3629966965,"remaining_time":0.2969972971},
{"learn":[0.02265412246],"iteration":55,"passed_time":0.3664608954,"remaining_time":0.2879335606},
{"learn":[0.0221172596],"iteration":56,"passed_time":0.3699111416,"remaining_time":0.2790557735},
{"learn":[0.02191939105],"iteration":57,"passed_time":0.3760990713,"remaining_time":0.2723476033},
{"learn":[0.02156992385],"iteration":58,"passed_time":0.3790846169,"remaining_time":0.2634316829},
{"learn":[0.02103250827],"iteration":59,"passed_time":0.3821449729,"remaining_time":0.2547633152},
{"learn":[0.02064988514],"iteration":60,"passed_time":0.3852368361,"remaining_time":0.2462989608},
{"learn":[0.01969215442],"iteration":61,"passed_time":0.3916639903,"remaining_time":0.2400521231},
{"learn":[0.01945151336],"iteration":62,"passed_time":0.3948800834,"remaining_time":0.2319136998},
{"learn":[0.01920515588],"iteration":63,"passed_time":0.3987438507,"remaining_time":0.224293416},
{"learn":[0.01888572703],"iteration":64,"passed_time":0.4032292426,"remaining_time":0.2171234383},
{"learn":[0.01838849819],"iteration":65,"passed_time":0.4092028339,"remaining_time":0.2108014599},
{"learn":[0.01818196573],"iteration":66,"passed_time":0.4126123223,"remaining_time":0.2032269647},
{"learn":[0.0177603347],"iteration":67,"passed_time":0.4175274511,"remaining_time":0.1964835064},
{"learn":[0.01751793616],"iteration":68,"passed_time":0.4245471654,"remaining_time":0.1907385815},
{"learn":[0.01721757978],"iteration":69,"passed_time":0.4275429679,"remaining_time":0.1832327005},
{"learn":[0.01670717716],"iteration":70,"passed_time":0.430643159,"remaining_time":0.1758965016},
{"learn":[0.01645349248],"iteration":71,"passed_time":0.4341092268,"remaining_time":0.1688202549},
{"learn":[0.01616947022],"iteration":72,"passed_time":0.4405514966,"remaining_time":0.1629437042},
{"learn":[0.01594589012],"iteration":73,"passed_time":0.4468023759,"remaining_time":0.1569846186},
{"learn":[0.01550743096],"iteration":74,"passed_time":0.4501352518,"remaining_time":0.1500450839},
{"learn":[0.01519331605],"iteration":75,"passed_time":0.4556282897,"remaining_time":0.1438826178},
{"learn":[0.01493704657],"iteration":76,"passed_time":0.4587064246,"remaining_time":0.1370162047},
{"learn":[0.01458566762],"iteration":77,"passed_time":0.4619134368,"remaining_time":0.130283277},
{"learn":[0.01447176118],"iteration":78,"passed_time":0.4650187467,"remaining_time":0.1236125782},
{"learn":[0.01417949069],"iteration":79,"passed_time":0.4707141743,"remaining_time":0.1176785436},
{"learn":[0.0138524007],"iteration":80,"passed_time":0.4742656661,"remaining_time":0.1112475019},
{"learn":[0.01371986754],"iteration":81,"passed_time":0.4773341977,"remaining_time":0.1047806776},
{"learn":[0.01351611345],"iteration":82,"passed_time":0.4805315625,"remaining_time":0.09842212727},
{"learn":[0.0133975019],"iteration":83,"passed_time":0.4856881455,"remaining_time":0.09251202771},
{"learn":[0.01318131778],"iteration":84,"passed_time":0.4888600113,"remaining_time":0.08626941376},
{"learn":[0.01311836761],"iteration":85,"passed_time":0.4919366859,"remaining_time":0.0800827163},
{"learn":[0.01286809575],"iteration":86,"passed_time":0.4948377995,"remaining_time":0.07394128038},
{"learn":[0.01274196713],"iteration":87,"passed_time":0.4980777904,"remaining_time":0.06791969869},
{"learn":[0.01255625],"iteration":88,"passed_time":0.5034557878,"remaining_time":0.06222487265},
{"learn":[0.0124436744],"iteration":89,"passed_time":0.506794404,"remaining_time":0.05631048933},
{"learn":[0.01231386994],"iteration":90,"passed_time":0.5097052848,"remaining_time":0.05041041278},
{"learn":[0.01223158275],"iteration":91,"passed_time":0.5123254912,"remaining_time":0.04455004271},
{"learn":[0.01214713234],"iteration":92,"passed_time":0.5147915824,"remaining_time":0.03874775351},
{"learn":[0.01205718662],"iteration":93,"passed_time":0.5203078237,"remaining_time":0.03321113768},
{"learn":[0.01171960943],"iteration":94,"passed_time":0.5229079202,"remaining_time":0.02752146949},
{"learn":[0.01148901326],"iteration":95,"passed_time":0.5257151478,"remaining_time":0.02190479782},
{"learn":[0.01135241803],"iteration":96,"passed_time":0.5290307137,"remaining_time":0.01636177465},
{"learn":[0.0112796064],"iteration":97,"passed_time":0.5349409763,"remaining_time":0.01091716278},
{"learn":[0.01109942752],"iteration":98,"passed_time":0.5377557787,"remaining_time":0.005431876552},
{"learn":[0.01079888613],"iteration":99,"passed_time":0.5404511512,"remaining_time":0}
]}